zensols/rend/resources/app.conf
zensols/rend/resources/default.conf
zensols/rend/resources/obj.conf
zensols/rend/resources/show-preview.scpt
zensols/rend/resources/show-safari-multi.scpt
zensols/rend/resources/show-safari.scpt
zensols/rend/__init__.py
zensols/rend/app.py
zensols/rend/browser.py
zensols/rend/cli.py
zensols/rend/darwin.py
zensols/rend/default.py
zensols/rend/df.py
zensols/rend/domain.py
zensols_rend-1.3.1.dist-info/METADATA
zensols_rend-1.3.1.dist-info/WHEEL
zensols_rend-1.3.1.dist-info/entry_points.txt
zensols_rend-1.3.1.dist-info/licenses/LICENSE.md
zensols_rend-1.3.1.dist-info/RECORD
