Metadata-Version: 2.3
Name: zensols_rend
Version: 1.3.1
Summary: Invoke native applications to view and render data from files.
Project-URL: Homepage, https://github.com/plandes/rend
Project-URL: Documentation, https://plandes.github.io/rend
Project-URL: Repository, https://github.com/plandes/rend.git
Project-URL: Issues, https://github.com/plandes/rend/issues
Project-URL: Changelog, https://github.com/plandes/rend/blob/master/CHANGELOG.md
Author-email: Paul Landes <landes@mailc.net>
License: MIT
Keywords: macOS,pdf,tooling,web browser
Requires-Python: <3.15,>=3.11
Requires-Dist: dash-bootstrap-components~=2.0.3
Requires-Dist: dash~=3.0.4
Requires-Dist: openpyxl~=3.1.5
Requires-Dist: screeninfo~=0.8.1
Requires-Dist: waitress~=3.0.2
Requires-Dist: zensols-datdesc~=1.4.2
